mycal_7/__init__.py
mycal_7-0.1.dist-info/METADATA
mycal_7-0.1.dist-info/WHEEL
mycal_7-0.1.dist-info/license.txt
mycal_7-0.1.dist-info/top_level.txt
mycal_7-0.1.dist-info/RECORD
