Metadata-Version: 2.1
Name: mycal-7
Version: 0.1
Summary: A BASIC ADDITIVE CALCULATOR
Home-page: UNKNOWN
Author: KAILASH BISHT
Author-email: rockstarksb123@gmail.com
License: UNKNOWN
Platform: UNKNOWN
